unifhycontrib_gr4-0.1.1-py3.8-nspkg.pth
unifhycontrib/gr4/__init__.py
unifhycontrib/gr4/openwater.py
unifhycontrib/gr4/subsurface.py
unifhycontrib/gr4/surfacelayer.py
unifhycontrib/gr4/version.py
unifhycontrib_gr4-0.1.1.dist-info/METADATA
unifhycontrib_gr4-0.1.1.dist-info/WHEEL
unifhycontrib_gr4-0.1.1.dist-info/namespace_packages.txt
unifhycontrib_gr4-0.1.1.dist-info/top_level.txt
unifhycontrib_gr4-0.1.1.dist-info/RECORD
