Metadata-Version: 2.1
Name: unifhycontrib-gr4
Version: 0.1.1
Summary: unifhy components for the GR4 model
Author: Thibault Hallouin
License: GPL-2.0
Project-URL: Source Code, https://github.com/unifhy-org/unifhycontrib-gr4
Platform: UNKNOWN
Classifier: Development Status :: 4 - Beta
Classifier: Natural Language :: English
Classifier: Topic :: Scientific/Engineering :: Hydrology
Requires-Dist: unifhy (>=0.1.0)
